vlm_recog/__init__.py
vlm_recog/bbox_utils.py
vlm_recog/detection.py
vlm_recog/models.py
vlm_recog/py.typed
vlm_recog/visualization.py
vlm_recog-0.2.2.dist-info/METADATA
vlm_recog-0.2.2.dist-info/WHEEL
vlm_recog-0.2.2.dist-info/licenses/LICENSE
vlm_recog-0.2.2.dist-info/RECORD
