Metadata-Version: 2.4
Name: vlm-recog
Version: 0.2.2
Summary: Add your description here
Author-email: neka-nat <nekanat.stock@gmail.com>
License-File: LICENSE
Requires-Python: >=3.11
Requires-Dist: google-genai>=1.32.0
Requires-Dist: loguru>=0.7.3
Requires-Dist: numpy<=2.2.6
Requires-Dist: pillow>=11.3.0
Requires-Dist: pydantic>=2.11.7
